[
  {
    "id": "UI2-CUT-001",
    "file": "UI2-CUT-001_古风UI切片候选.png",
    "bbox": [
      3,
      5,
      358,
      248
    ],
    "size": [
      355,
      243
    ],
    "area": 68842
  },
  {
    "id": "UI2-CUT-002",
    "file": "UI2-CUT-002_古风UI切片候选.png",
    "bbox": [
      361,
      5,
      717,
      248
    ],
    "size": [
      356,
      243
    ],
    "area": 68878
  },
  {
    "id": "UI2-CUT-003",
    "file": "UI2-CUT-003_古风UI切片候选.png",
    "bbox": [
      722,
      17,
      1014,
      237
    ],
    "size": [
      292,
      220
    ],
    "area": 53707
  },
  {
    "id": "UI2-CUT-004",
    "file": "UI2-CUT-004_古风UI切片候选.png",
    "bbox": [
      0,
      249,
      346,
      384
    ],
    "size": [
      346,
      135
    ],
    "area": 33607
  },
  {
    "id": "UI2-CUT-005",
    "file": "UI2-CUT-005_古风UI切片候选.png",
    "bbox": [
      338,
      249,
      687,
      384
    ],
    "size": [
      349,
      135
    ],
    "area": 33683
  },
  {
    "id": "UI2-CUT-006",
    "file": "UI2-CUT-006_古风UI切片候选.png",
    "bbox": [
      678,
      249,
      1024,
      384
    ],
    "size": [
      346,
      135
    ],
    "area": 33694
  },
  {
    "id": "UI2-CUT-007",
    "file": "UI2-CUT-007_古风UI切片候选.png",
    "bbox": [
      301,
      387,
      501,
      503
    ],
    "size": [
      200,
      116
    ],
    "area": 18347
  },
  {
    "id": "UI2-CUT-008",
    "file": "UI2-CUT-008_古风UI切片候选.png",
    "bbox": [
      523,
      387,
      723,
      503
    ],
    "size": [
      200,
      116
    ],
    "area": 18332
  },
  {
    "id": "UI2-CUT-009",
    "file": "UI2-CUT-009_古风UI切片候选.png",
    "bbox": [
      26,
      515,
      331,
      576
    ],
    "size": [
      305,
      61
    ],
    "area": 12941
  },
  {
    "id": "UI2-CUT-010",
    "file": "UI2-CUT-010_古风UI切片候选.png",
    "bbox": [
      356,
      510,
      669,
      582
    ],
    "size": [
      313,
      72
    ],
    "area": 13189
  },
  {
    "id": "UI2-CUT-011",
    "file": "UI2-CUT-011_古风UI切片候选.png",
    "bbox": [
      695,
      517,
      996,
      574
    ],
    "size": [
      301,
      57
    ],
    "area": 11600
  },
  {
    "id": "UI2-CUT-012",
    "file": "UI2-CUT-012_古风UI切片候选.png",
    "bbox": [
      27,
      576,
      331,
      637
    ],
    "size": [
      304,
      61
    ],
    "area": 12872
  },
  {
    "id": "UI2-CUT-013",
    "file": "UI2-CUT-013_古风UI切片候选.png",
    "bbox": [
      356,
      570,
      669,
      643
    ],
    "size": [
      313,
      73
    ],
    "area": 13233
  },
  {
    "id": "UI2-CUT-014",
    "file": "UI2-CUT-014_古风UI切片候选.png",
    "bbox": [
      695,
      578,
      996,
      635
    ],
    "size": [
      301,
      57
    ],
    "area": 11542
  },
  {
    "id": "UI2-CUT-015",
    "file": "UI2-CUT-015_古风UI切片候选.png",
    "bbox": [
      26,
      637,
      331,
      698
    ],
    "size": [
      305,
      61
    ],
    "area": 12892
  },
  {
    "id": "UI2-CUT-016",
    "file": "UI2-CUT-016_古风UI切片候选.png",
    "bbox": [
      355,
      631,
      669,
      704
    ],
    "size": [
      314,
      73
    ],
    "area": 13211
  },
  {
    "id": "UI2-CUT-017",
    "file": "UI2-CUT-017_古风UI切片候选.png",
    "bbox": [
      695,
      639,
      996,
      696
    ],
    "size": [
      301,
      57
    ],
    "area": 11601
  },
  {
    "id": "UI2-CUT-018",
    "file": "UI2-CUT-018_古风UI切片候选.png",
    "bbox": [
      0,
      704,
      500,
      896
    ],
    "size": [
      500,
      192
    ],
    "area": 74649
  },
  {
    "id": "UI2-CUT-019",
    "file": "UI2-CUT-019_古风UI切片候选.png",
    "bbox": [
      502,
      708,
      763,
      773
    ],
    "size": [
      261,
      65
    ],
    "area": 8916
  },
  {
    "id": "UI2-CUT-020",
    "file": "UI2-CUT-020_古风UI切片候选.png",
    "bbox": [
      765,
      708,
      1024,
      773
    ],
    "size": [
      259,
      65
    ],
    "area": 8914
  },
  {
    "id": "UI2-CUT-021",
    "file": "UI2-CUT-021_古风UI切片候选.png",
    "bbox": [
      502,
      768,
      763,
      832
    ],
    "size": [
      261,
      64
    ],
    "area": 8928
  },
  {
    "id": "UI2-CUT-022",
    "file": "UI2-CUT-022_古风UI切片候选.png",
    "bbox": [
      765,
      768,
      1024,
      832
    ],
    "size": [
      259,
      64
    ],
    "area": 8908
  },
  {
    "id": "UI2-CUT-023",
    "file": "UI2-CUT-023_古风UI切片候选.png",
    "bbox": [
      502,
      827,
      763,
      892
    ],
    "size": [
      261,
      65
    ],
    "area": 8916
  },
  {
    "id": "UI2-CUT-024",
    "file": "UI2-CUT-024_古风UI切片候选.png",
    "bbox": [
      766,
      827,
      1024,
      892
    ],
    "size": [
      258,
      65
    ],
    "area": 8882
  },
  {
    "id": "UI2-CUT-025",
    "file": "UI2-CUT-025_古风UI切片候选.png",
    "bbox": [
      501,
      899,
      553,
      976
    ],
    "size": [
      52,
      77
    ],
    "area": 881
  },
  {
    "id": "UI2-CUT-026",
    "file": "UI2-CUT-026_古风UI切片候选.png",
    "bbox": [
      631,
      913,
      725,
      1008
    ],
    "size": [
      94,
      95
    ],
    "area": 4926
  },
  {
    "id": "UI2-CUT-027",
    "file": "UI2-CUT-027_古风UI切片候选.png",
    "bbox": [
      734,
      915,
      826,
      1006
    ],
    "size": [
      92,
      91
    ],
    "area": 4649
  },
  {
    "id": "UI2-CUT-028",
    "file": "UI2-CUT-028_古风UI切片候选.png",
    "bbox": [
      557,
      957,
      626,
      1023
    ],
    "size": [
      69,
      66
    ],
    "area": 936
  }
]