[
  {
    "file": "01_优先叠层候选/VID-OV-CLOUD-001_水墨云雾叠层候选.mp4",
    "width": 1280,
    "height": 720,
    "duration": 8.0,
    "size_mb": 1.97,
    "poster": "预览图/VID-OV-CLOUD-001_水墨云雾叠层候选_poster.jpg"
  },
  {
    "file": "01_优先叠层候选/VID-OV-CRACK-001_墨裂线开合叠层候选.mp4",
    "width": 1280,
    "height": 720,
    "duration": 8.0,
    "size_mb": 2.11,
    "poster": "预览图/VID-OV-CRACK-001_墨裂线开合叠层候选_poster.jpg"
  },
  {
    "file": "01_优先叠层候选/VID-OV-DUST-001_纸面落尘叠层候选.mp4",
    "width": 1280,
    "height": 720,
    "duration": 4.0,
    "size_mb": 1.22,
    "poster": "预览图/VID-OV-DUST-001_纸面落尘叠层候选_poster.jpg"
  },
  {
    "file": "01_优先叠层候选/VID-OV-GOLD-001_暗金尘粒黑底候选.mp4",
    "width": 1280,
    "height": 720,
    "duration": 4.0,
    "size_mb": 1.24,
    "poster": "预览图/VID-OV-GOLD-001_暗金尘粒黑底候选_poster.jpg"
  },
  {
    "file": "01_优先叠层候选/VID-OV-MAPREVEAL-001_帛雾显影地图痕迹候选.mp4",
    "width": 1280,
    "height": 720,
    "duration": 4.0,
    "size_mb": 1.03,
    "poster": "预览图/VID-OV-MAPREVEAL-001_帛雾显影地图痕迹候选_poster.jpg"
  },
  {
    "file": "01_优先叠层候选/VID-OV-SAND-001_黑底风沙叠层候选.mp4",
    "width": 1280,
    "height": 720,
    "duration": 8.0,
    "size_mb": 2.09,
    "poster": "预览图/VID-OV-SAND-001_黑底风沙叠层候选_poster.jpg"
  },
  {
    "file": "01_优先叠层候选/VID-OV-SEAL-001_朱砂印裂纹脉冲候选.mp4",
    "width": 1280,
    "height": 720,
    "duration": 4.0,
    "size_mb": 1.22,
    "poster": "预览图/VID-OV-SEAL-001_朱砂印裂纹脉冲候选_poster.jpg"
  },
  {
    "file": "02_转场背景候选/VID-BG-MAP-001_帛书九州图动态背景候选.mp4",
    "width": 1280,
    "height": 720,
    "duration": 6.0,
    "size_mb": 1.38,
    "poster": "预览图/VID-BG-MAP-001_帛书九州图动态背景候选_poster.jpg"
  },
  {
    "file": "02_转场背景候选/VID-BG-PARCHMENTMAP-001_古帛地图背景候选.mp4",
    "width": 1280,
    "height": 720,
    "duration": 10.0,
    "size_mb": 2.4,
    "poster": "预览图/VID-BG-PARCHMENTMAP-001_古帛地图背景候选_poster.jpg"
  },
  {
    "file": "02_转场背景候选/VID-BG-SMOKE-001_旧帛灰烟背景候选.mp4",
    "width": 1280,
    "height": 720,
    "duration": 10.0,
    "size_mb": 2.43,
    "poster": "预览图/VID-BG-SMOKE-001_旧帛灰烟背景候选_poster.jpg"
  },
  {
    "file": "02_转场背景候选/VID-TR-PARCHMENT-001_旧帛展开暗场候选.mp4",
    "width": 1280,
    "height": 720,
    "duration": 4.0,
    "size_mb": 0.93,
    "poster": "预览图/VID-TR-PARCHMENT-001_旧帛展开暗场候选_poster.jpg"
  },
  {
    "file": "02_转场背景候选/VID-TR-RIFT-001_裂隙墨洗过场候选.mp4",
    "width": 1280,
    "height": 720,
    "duration": 8.0,
    "size_mb": 1.85,
    "poster": "预览图/VID-TR-RIFT-001_裂隙墨洗过场候选_poster.jpg"
  },
  {
    "file": "02_转场背景候选/VID-TR-ROAD-001_古道灰雾过场候选.mp4",
    "width": 1280,
    "height": 720,
    "duration": 8.0,
    "size_mb": 2.02,
    "poster": "预览图/VID-TR-ROAD-001_古道灰雾过场候选_poster.jpg"
  },
  {
    "file": "03_待判断候选/VID-MISC-ASHINK-001_灰烬淡墨痕候选.mp4",
    "width": 1280,
    "height": 720,
    "duration": 8.0,
    "size_mb": 1.85,
    "poster": "预览图/VID-MISC-ASHINK-001_灰烬淡墨痕候选_poster.jpg"
  },
  {
    "file": "03_待判断候选/VID-MISC-UNMAPPED_Ancient_China_ink_painting_lands…_202606211449.mp4",
    "width": 1280,
    "height": 720,
    "duration": 10.0,
    "size_mb": 2.35,
    "poster": "预览图/VID-MISC-UNMAPPED_Ancient_China_ink_painting_lands…_202606211449_poster.jpg"
  },
  {
    "file": "03_待判断候选/VID-MISC-UNMAPPED_Dark_silk_parchment_background_i…_202606211449.mp4",
    "width": 1280,
    "height": 720,
    "duration": 10.0,
    "size_mb": 2.42,
    "poster": "预览图/VID-MISC-UNMAPPED_Dark_silk_parchment_background_i…_202606211449_poster.jpg"
  }
]